practo/__init__.py
practo-0.1.2.dist-info/LICENCE.txt
practo-0.1.2.dist-info/METADATA
practo-0.1.2.dist-info/WHEEL
practo-0.1.2.dist-info/top_level.txt
practo-0.1.2.dist-info/RECORD
