Metadata-Version: 2.1
Name: practo
Version: 0.1.2
Summary: It contains Algorithms
Home-page: 
Author: Hemanshu Pathak
Author-email: himanshu2002pathak@gmail.com
License: MIT
Keywords: algorithms
Classifier: Development Status :: 5 - Production/Stable
Classifier: Intended Audience :: Education
Classifier: Operating System :: Microsoft :: Windows :: Windows 10
Classifier: License :: OSI Approved :: MIT License
Classifier: Programming Language :: Python :: 3
License-File: LICENCE.txt
